README
setup.py
src/TailSpin.egg-info/PKG-INFO
src/TailSpin.egg-info/SOURCES.txt
src/TailSpin.egg-info/dependency_links.txt
src/TailSpin.egg-info/native_libs.txt
src/TailSpin.egg-info/requires.txt
src/TailSpin.egg-info/top_level.txt
src/tailspin/__init__.py
src/tailspin/fast.py
src/tailspin/fast_h.c
src/tailspin/fastlazy.py
src/tailspin/fastlazy_h.c
src/tailspin/lazy.py
src/tailspin/plain.py
test/test.py
