Metadata-Version: 1.0
Name: TailSpin
Version: 0.1.1
Summary: Efficient Tail Recursion
Home-page: http://xavecode.mit.edu/tailspin/
Author: Xavid Pretzer
Author-email: xavid@mit.edu
License: MIT
Keywords: tail recursion
Platform: UNKNOWN
Classifier: Development Status :: 4 - Beta
Classifier: Intended Audience :: Developers
Classifier: License :: OSI Approved :: MIT License
Classifier: Operating System :: OS Independent
Classifier: Topic :: Software Development :: Libraries :: Python Modules
